bible/__init__.py
bible/cli.py
jc_bible-1.0.1.dist-info/licenses/LICENSE
jc_bible-1.0.1.dist-info/METADATA
jc_bible-1.0.1.dist-info/WHEEL
jc_bible-1.0.1.dist-info/entry_points.txt
jc_bible-1.0.1.dist-info/top_level.txt
jc_bible-1.0.1.dist-info/RECORD
