Metadata-Version: 2.4
Name: jc-bible
Version: 1.0.1
Summary: A simple bible utility.
Author-email: Jeff Clough <jeff@cloughcottage.com>
License: MIT
Project-URL: Homepage, https://github.com/jeffclough/bible
Project-URL: Repository, https://github.com/jeffclough/bible.git
Project-URL: Bug Tracker, https://github.com/jeffclough/bible/issues
Keywords: bible,cli
Classifier: Programming Language :: Python :: 3
Classifier: License :: OSI Approved :: MIT License
Classifier: Operating System :: OS Independent
Classifier: Development Status :: 5 - Production/Stable
Requires-Python: >=3.11
License-File: LICENSE
Requires-Dist: jc-debug
Requires-Dist: jc-handy-helpers
Requires-Dist: requests
Requires-Dist: tomlkit
Dynamic: license-file
